streamlit_html_components/__init__.py
streamlit_html_components/asset_loader.py
streamlit_html_components/cache_manager.py
streamlit_html_components/config.py
streamlit_html_components/config_v2.py
streamlit_html_components/core.py
streamlit_html_components/core_v2.py
streamlit_html_components/dev_server.py
streamlit_html_components/diagnostics.py
streamlit_html_components/exceptions.py
streamlit_html_components/file_watcher.py
streamlit_html_components/registry.py
streamlit_html_components/renderer.py
streamlit_html_components/security.py
streamlit_html_components/serialization.py
streamlit_html_components/template_engine.py
streamlit_html_components/validation.py
streamlit_html_components/validators.py
streamlit_html_components/bidirectional/__init__.py
streamlit_html_components/bidirectional/bridge.py
streamlit_html_components/bidirectional/sync.py
streamlit_html_components-0.3.2.dist-info/licenses/LICENSE
streamlit_html_components-0.3.2.dist-info/METADATA
streamlit_html_components-0.3.2.dist-info/WHEEL
streamlit_html_components-0.3.2.dist-info/top_level.txt
streamlit_html_components-0.3.2.dist-info/RECORD
