Metadata-Version: 2.4
Name: streamlit-html-components
Version: 0.3.2
Summary: Use traditional HTML/CSS/JS file structure with Streamlit - now with hot reload, state management, and validation
Author-email: CJ Carito <cjcarito15@gmail.com>
License: MIT
Project-URL: Homepage, https://github.com/civarry/streamlit-html-components
Project-URL: Documentation, https://github.com/civarry/streamlit-html-components#readme
Project-URL: Repository, https://github.com/civarry/streamlit-html-components
Project-URL: Issues, https://github.com/civarry/streamlit-html-components/issues
Keywords: streamlit,components,html,css,javascript,web,framework
Classifier: Development Status :: 3 - Alpha
Classifier: Intended Audience :: Developers
Classifier: License :: OSI Approved :: MIT License
Classifier: Programming Language :: Python :: 3
Classifier: Programming Language :: Python :: 3.10
Classifier: Programming Language :: Python :: 3.11
Classifier: Programming Language :: Python :: 3.12
Classifier: Topic :: Software Development :: Libraries :: Python Modules
Requires-Python: >=3.10
License-File: LICENSE
Requires-Dist: streamlit>=1.52.0
Requires-Dist: jinja2>=3.1.0
Requires-Dist: pydantic>=2.0.0
Provides-Extra: dev
Requires-Dist: pytest>=7.0; extra == "dev"
Requires-Dist: pytest-cov>=4.0; extra == "dev"
Requires-Dist: black>=23.0; extra == "dev"
Requires-Dist: ruff>=0.1.0; extra == "dev"
Requires-Dist: mypy>=1.0; extra == "dev"
Provides-Extra: docs
Requires-Dist: sphinx>=5.0; extra == "docs"
Requires-Dist: sphinx-rtd-theme>=1.0; extra == "docs"
Dynamic: license-file
